mzgeohash/__init__.py
mzgeohash/geohash.py
mzgeohash/test_geohash.py
mzgeohash-1.1.0.dist-info/METADATA
mzgeohash-1.1.0.dist-info/WHEEL
mzgeohash-1.1.0.dist-info/licenses/LICENSE.txt
mzgeohash-1.1.0.dist-info/RECORD
