Metadata-Version: 2.4
Name: mzgeohash
Version: 1.1.0
Summary: Mapzen Geohash
Project-URL: Homepage, https://github.com/transitland/mapzen-geohash/blob/master/mzgeohash/geohash.py
Author-email: Ian Rees <ian@ianrees.net>
License-Expression: MIT
License-File: LICENSE.txt
Classifier: Development Status :: 4 - Beta
Classifier: Programming Language :: Python
Requires-Python: >=3.8
